MetaQ/__init__.py
MetaQ/data_utils.py
MetaQ/engine.py
MetaQ/eval_utils.py
MetaQ/main.py
MetaQ/model.py
MetaQ-sc/__init__.py
MetaQ-sc/data_utils.py
MetaQ-sc/engine.py
MetaQ-sc/eval_utils.py
MetaQ-sc/main.py
MetaQ-sc/model.py
MetaQ_sc/__init__.py
MetaQ_sc/data_utils.py
MetaQ_sc/engine.py
MetaQ_sc/eval_utils.py
MetaQ_sc/main.py
MetaQ_sc/model.py
MetaQ_sc-1.0.6.dist-info/LICENSE.txt
MetaQ_sc-1.0.6.dist-info/METADATA
MetaQ_sc-1.0.6.dist-info/WHEEL
MetaQ_sc-1.0.6.dist-info/top_level.txt
MetaQ_sc-1.0.6.dist-info/RECORD
